LICENSE
README.md
pyproject.toml
setup.py
mwcleric/__init__.py
mwcleric/auth_credentials.py
mwcleric/errors.py
mwcleric/fandom_client.py
mwcleric/page_modifier.py
mwcleric/template_modifier.py
mwcleric/wiki_client.py
mwcleric/wikigg_client.py
mwcleric.egg-info/PKG-INFO
mwcleric.egg-info/SOURCES.txt
mwcleric.egg-info/dependency_links.txt
mwcleric.egg-info/requires.txt
mwcleric.egg-info/top_level.txt
mwcleric/clients/__init__.py
mwcleric/clients/cargo_client.py
mwcleric/clients/session_manager.py
mwcleric/clients/site.py
mwcleric/models/__init__.py
mwcleric/models/namespace.py
mwcleric/models/simple_page.py
mwcleric/models/logs/__init__.py
mwcleric/models/logs/log_entry.py
mwcleric/models/logs/move_log_entry.py