Metadata-Version: 2.1
Name: mwcleric
Version: 0.9.0
Summary: River's mwclient wrapper
Home-page: https://github.com/RheingoldRiver/mwcleric
Author: RheingoldRiver
Author-email: river.esports@gmail.com
Requires-Python: >=3.6
License-File: LICENSE
Requires-Dist: mwparserfromhell
Requires-Dist: pytz
Requires-Dist: mwclient>=0.10.1
